posym-1.2.4.dist-info/LICENSE
posym-1.2.4.dist-info/WHEEL
posym-1.2.4.dist-info/top_level.txt
posym-1.2.4.dist-info/METADATA
posym-1.2.4.dist-info/RECORD
posym.libs/libgomp-65f46eca.so.1.0.0
posym/basis.py
posym/integrals.cpython-38-i386-linux-gnu.so
posym/algebra.py
posym/pointgroup.py
posym/generate_tables.py
posym/config.py
posym/ir_tables.py
posym/__init__.py
posym/errors.py
posym/tools.py
posym/permutation/permutations.cpython-38-i386-linux-gnu.so
posym/permutation/__init__.py
posym/permutation/hungarian.py
posym/operations/inversion.py
posym/operations/reflection.py
posym/operations/irotation.py
posym/operations/identity.py
posym/operations/products.py
posym/operations/rotation.py
posym/operations/__init__.py
