Metadata-Version: 2.1
Name: posym
Version: 1.2.4
Summary: posym module
Home-page: https://github.com/abelcarreras/posym
Author: Abel Carreras
Author-email: abelcarreras83@gmail.com
License: MIT License
License-File: LICENSE
Requires-Dist: numpy
Requires-Dist: scipy
Requires-Dist: pandas
Requires-Dist: PyYaml
